Workbook

Sheet Model_Logic
A1: Wonder Cement — Illustrative Scenario Model (FY 2024-25)
A2: Company | B2: Wonder Cement Limited (illustrative model for product testing — not an audited statement)
A3: Purpose | B3: Driver-based grey-cement P&L so scenario levers (volume, price, fuel, freight) recompute the full stack with formulas.
A4: Currency / Unit | B4: INR Crore for P&L amounts. Volume in million tonnes (MT). Realization & variable costs in ₹ / tonne.
A5: Public scale anchor | B5: Roughly aligned to FY25 order of magnitude: ~₹7,365 Cr revenue, ~₹505 Cr PAT, ~14 MT sales, ~₹5,260/t list realization. | C5: Synthetic — for testing only
A7: CALCULATION CHAIN | B7: How numbers flow across sheets | C7: Sheet / Cell
A8: 1. Drivers | B8: Edit yellow cells only on Assumptions. Everything else is formula-driven. | C8: Assumptions!B7:B22
A9: 2. Volume bridge | B9: Sales volume MT × product mix → cement tonnes sold by grade. | C9: Volume_Mix
A10: 3. Revenue | B10: Revenue (₹ Cr) = Sales volume (MT) × Net realization (₹/t) ÷ 10 | C10: P&L!C8
A11: 4. Variable costs | B11: Each variable line = Volume (MT) × ₹/t rate ÷ 10 | C11: Cost_Build!C6:C11
A12: 5. Contribution | B12: Contribution = Net revenue − total variable costs | C12: P&L!C20
A13: 6. Fixed opex | B13: Employee + other cash fixed opex (₹ Cr) | C13: P&L!C24:C25
A14: 7. EBITDA | B14: EBITDA = Contribution − cash fixed opex + other income | C14: P&L!C28
A15: 8. EBIT / PBT / PAT | B15: EBIT = EBITDA − D&A; PBT = EBIT − finance; Tax = PBT × rate; PAT = PBT − Tax | C15: P&L!C29:C34
A17: UNIT MATH | B17: Why ÷ 10?
A18: Identity | B18: 1 MT × ₹1/tonne = ₹10 lakh = ₹0.1 Cr → Revenue_Cr = Volume_MT × ₹/t ÷ 10 | C18: Keep this identity when changing drivers
A20: SCENARIO IDEAS | B20: Natural-language prompts that should move yellow levers | C20: Expected direction
A21: Volume +10% | B21: Increase cement sales volume by 10% | C21: Revenue↑, variable costs↑, PAT↑ (operating leverage)
A22: Price −₹200/t | B22: Cut blended realization by 200 rupees per tonne | C22: Revenue↓, margins compress
A23: Fuel spike +15% | B23: Raise fuel & power cost per tonne by 15% | C23: EBITDA↓
A24: Freight +₹50/t | B24: Raise outbound freight by ₹50/t | C24: Contribution↓
A26: DISCLAIMER | B26: Figures are rounded, synthetic, and constructed for Scenario Modeling tests. Do not use for investment decisions.

Sheet Assumptions
A1: Driver / Assumption | B1: Value | C1: Unit | D1: Notes (edit yellow cells — these are scenario levers)
A2: META
A3: Company | B3: Wonder Cement Limited | D3: RK Group — grey cement (Nimbahera + grinding units)
A4: Statement period | B4: FY 2024-25 | D4: All figures in INR Crore unless noted
A5: Denomination banner | B5: All figures in INR Crore | D5: Kept for parser denomination detection
A6: VOLUME & PRICE LEVERS
A7: Cement sales volume | B7: 14 | C7: MT | D7: Yellow lever — annual cement sold (million tonnes)
A8: Blended realization | B8: 5260 | C8: ₹ / tonne | D8: Yellow lever — list / trade realization before rebate
A9: Trade discount & dealer rebate | B9: 80 | C9: ₹ / tonne | D9: Deducted from blended realization → net realization
A10: Limestone & raw materials | B10: 420 | C10: ₹ / tonne | D10: Yellow lever — variable raw material cost
A11: Fuel & power (petcoke/coal/grid) | B11: 980 | C11: ₹ / tonne | D11: Yellow lever — kiln + grinding energy
A12: Packing materials | B12: 95 | C12: ₹ / tonne | D12: Bags & packing
A13: Inbound logistics (mine/plant) | B13: 110 | C13: ₹ / tonne | D13: Limestone / coal inbound
A14: Outbound freight to market | B14: 620 | C14: ₹ / tonne | D14: Yellow lever — primary + secondary freight
A15: Other variable manufacturing | B15: 140 | C15: ₹ / tonne | D15: Stores, consumables, variable plant costs
A16: FIXED COST & BELOW-EBITDA
A17: Employee benefits expense | B17: 274 | C17: ₹ Cr | D17: Salaries, PF, welfare — largely fixed
A18: Other cash fixed opex | B18: 980 | C18: ₹ Cr | D18: Admin, selling overhead, repairs (cash)
A19: Depreciation & amortization | B19: 541 | C19: ₹ Cr | D19: Plant, WHR, grinding units
A20: Finance cost | B20: 210 | C20: ₹ Cr | D20: Interest on borrowings
A21: Other income | B21: 54 | C21: ₹ Cr | D21: Interest / misc income
A22: Effective tax rate | B22: 0.32 | C22: % | D22: Tax / PBT (illustrative)
A24: DERIVED (do not edit)
A25: Net realization after rebate | B25: =B8-B9 -> 5180 | C25: ₹ / tonne | D25: = Blended realization − trade discount
A26: Total variable cost rate | B26: =B10+B11+B12+B13+B14+B15 -> 2365 | C26: ₹ / tonne | D26: = Sum of all ₹/t variable cost levers
A27: Contribution per tonne | B27: =B25-B26 -> 2815 | C27: ₹ / tonne | D27: = Net realization − total variable cost rate
A28: Revenue (₹ Cr) | B28: =B7*B25/10 -> 7252 | C28: ₹ Cr | D28: = Volume_MT × Net realization_₹/t ÷ 10
A29: Total variable costs (₹ Cr) | B29: =B7*B26/10 -> 3311 | C29: ₹ Cr | D29: = Volume_MT × Variable_₹/t ÷ 10
A31: PRIOR YEAR ANCHORS (FY24 hardcodes)
A32: FY24 cement sales volume | B32: 12.97 | C32: MT | D32: CARE FY24 sales volume reference
A33: FY24 net realization | B33: 5455 | C33: ₹ / tonne | D33: Implied from ~₹7,077 Cr / 12.97 MT
A34: FY24 total variable ₹/t | B34: 2480 | C34: ₹ / tonne | D34: Slightly higher energy intensity prior year
A35: FY24 employee benefits | B35: 257 | C35: ₹ Cr
A36: FY24 other cash fixed opex | B36: 1020 | C36: ₹ Cr
A37: FY24 D&A | B37: 495 | C37: ₹ Cr
A38: FY24 finance cost | B38: 225 | C38: ₹ Cr
A39: FY24 other income | B39: 32 | C39: ₹ Cr
A40: FY24 tax rate | B40: 0.329 | C40: %

Sheet Volume_Mix
A1: Product / Channel | B1: Mix % | C1: Volume (MT) | D1: FY24 Vol (MT) | E1: Logic
A2: Total cement sales | B2: 1 | C2: =Assumptions!B7 -> 14 | D2: =Assumptions!B32 -> 12.97 | E2: Master volume lever from Assumptions!B7
A3: OPC (Ordinary Portland) | B3: 0.35 | C3: =$C$2*B3 -> 4.9 | D3: =$D$2*B3 -> 4.5395 | E3: = Total volume × mix % (edit yellow mix)
A4: PPC (Portland Pozzolana) | B4: 0.55 | C4: =$C$2*B4 -> 7.7 | D4: =$D$2*B4 -> 7.1335 | E4: = Total volume × mix % (edit yellow mix)
A5: Specialty / other grey | B5: 0.1 | C5: =$C$2*B5 -> 1.4 | D5: =$D$2*B5 -> 1.297 | E5: = Total volume × mix % (edit yellow mix)
A7: Mix check (must = 100%) | B7: =B3+B4+B5 -> 1 | E7: If not 100%, fix yellow mix cells
A9: Capacity context
A10: Installed grinding capacity | B10: 21.5 | C10: MTPA | E10: Post Line-5 (~May 2025) public figure
A11: Capacity utilization | B11: =C2/B10 -> 0.65116279 | C11: % | E11: = Sales volume / installed capacity

Sheet Cost_Build
A1: Cost line | B1: ₹ / tonne | C1: FY25 (₹ Cr) | D1: FY24 (₹ Cr) | E1: Formula
A2: Sales volume (MT) | C2: =Assumptions!B7 -> 14 | D2: =Assumptions!B32 -> 12.97 | E2: From Assumptions
A3: Net realization ₹/t | B3: =Assumptions!B25 -> 5180 | C3: =Assumptions!B28 -> 7252 | D3: =Assumptions!B32*Assumptions!B33/10 -> 7075.135 | E3: Revenue bridge
A5: VARIABLE COSTS
A6: Limestone & raw materials | B6: =Assumptions!B10 -> 420 | C6: =$C$2*B6/10 -> 588 | D6: =$D$2*446.40/10 -> 578.9808 | E6: = Volume_MT × ₹/t ÷ 10
A7: Fuel & power | B7: =Assumptions!B11 -> 980 | C7: =$C$2*B7/10 -> 1372 | D7: =$D$2*1041.60/10 -> 1350.9552 | E7: = Volume_MT × ₹/t ÷ 10
A8: Packing materials | B8: =Assumptions!B12 -> 95 | C8: =$C$2*B8/10 -> 133 | D8: =$D$2*99.20/10 -> 128.6624 | E8: = Volume_MT × ₹/t ÷ 10
A9: Inbound logistics | B9: =Assumptions!B13 -> 110 | C9: =$C$2*B9/10 -> 154 | D9: =$D$2*124.00/10 -> 160.828 | E9: = Volume_MT × ₹/t ÷ 10
A10: Outbound freight | B10: =Assumptions!B14 -> 620 | C10: =$C$2*B10/10 -> 868 | D10: =$D$2*644.80/10 -> 836.3056 | E10: = Volume_MT × ₹/t ÷ 10
A11: Other variable manufacturing | B11: =Assumptions!B15 -> 140 | C11: =$C$2*B11/10 -> 196 | D11: =$D$2*124.00/10 -> 160.828 | E11: = Volume_MT × ₹/t ÷ 10
A12: Total variable costs | B12: =SUM(B6:B11) -> 2365 | C12: =SUM(C6:C11) -> 3311 | D12: =SUM(D6:D11) -> 3216.56 | E12: Must match Assumptions!B26 / B29
A14: Contribution (₹ Cr) | B14: =B3-B12 -> 2815 | C14: =C3-C12 -> 3941 | D14: =D3-D12 -> 3858.575 | E14: = Net revenue − total variable costs
A15: Contribution margin % | B15: =IF(B3=0,0,B14/B3) -> 0.54343629 | C15: =IF(C3=0,0,C14/C3) -> 0.54343629 | D15: =IF(D3=0,0,D14/D3) -> 0.54537122 | E15: Contribution / Net revenue

Sheet P&L
A1: Line item | B1: Section | C1: FY25 (₹ Cr) | D1: FY24 (₹ Cr) | E1: YoY % | F1: Calculation / source
A2: Wonder Cement Limited — Profit & Loss
A3: All figures in INR Crore | B3: Currency INR | C3: Unit Crore | F3: Green = formulas. Change yellow levers on Assumptions.
A5: Cement sales volume (MT) | B5: Volume | C5: =Assumptions!B7 -> 14 | D5: =Assumptions!B32 -> 12.97 | E5: =IF(D5=0,0,(C5-D5)/ABS(D5)) -> 0.079414032 | F5: Driver — not a P&L ₹ line
A6: Net realization (₹/t) | B6: Price | C6: =Assumptions!B25 -> 5180 | D6: =Assumptions!B33 -> 5455 | E6: =IF(D6=0,0,(C6-D6)/ABS(D6)) -> -0.050412466 | F6: After dealer rebate
A7: REVENUE
A8: Revenue from operations | B8: Revenue | C8: =Assumptions!B28 -> 7252 | D8: =Assumptions!B32*Assumptions!B33/10 -> 7075.135 | E8: =IF(D8=0,0,(C8-D8)/ABS(D8)) -> 0.02499811 | F8: = Volume × Net realization ÷ 10
A9: Other income | B9: Revenue | C9: =Assumptions!B21 -> 54 | D9: =Assumptions!B39 -> 32 | E9: =IF(D9=0,0,(C9-D9)/ABS(D9)) -> 0.6875 | F9: Assumptions lever
A10: Total income | B10: Revenue | C10: =C8+C9 -> 7306 | D10: =D8+D9 -> 7107.135 | E10: =IF(D10=0,0,(C10-D10)/ABS(D10)) -> 0.027981036 | F10: Revenue + other income
A12: VARIABLE COSTS
A13: Limestone & raw materials | B13: COGS | C13: =Cost_Build!C6 -> 588 | D13: =Cost_Build!D6 -> 578.9808 | E13: =IF(D13=0,0,(C13-D13)/ABS(D13)) -> 0.015577719 | F13: From Cost_Build
A14: Fuel & power | B14: COGS | C14: =Cost_Build!C7 -> 1372 | D14: =Cost_Build!D7 -> 1350.9552 | E14: =IF(D14=0,0,(C14-D14)/ABS(D14)) -> 0.015577719 | F14: Energy intensity lever
A15: Packing materials | B15: COGS | C15: =Cost_Build!C8 -> 133 | D15: =Cost_Build!D8 -> 128.6624 | E15: =IF(D15=0,0,(C15-D15)/ABS(D15)) -> 0.033713035
A16: Inbound logistics | B16: COGS | C16: =Cost_Build!C9 -> 154 | D16: =Cost_Build!D9 -> 160.828 | E16: =IF(D16=0,0,(C16-D16)/ABS(D16)) -> -0.042455294
A17: Outbound freight | B17: COGS | C17: =Cost_Build!C10 -> 868 | D17: =Cost_Build!D10 -> 836.3056 | E17: =IF(D17=0,0,(C17-D17)/ABS(D17)) -> 0.037898108 | F17: Freight lever
A18: Other variable manufacturing | B18: COGS | C18: =Cost_Build!C11 -> 196 | D18: =Cost_Build!D11 -> 160.828 | E18: =IF(D18=0,0,(C18-D18)/ABS(D18)) -> 0.21869326
A19: Total variable costs | B19: COGS | C19: =SUM(C13:C18) -> 3311 | D19: =SUM(D13:D18) -> 3216.56 | E19: =IF(D19=0,0,(C19-D19)/ABS(D19)) -> 0.029360559 | F19: Sum of variable lines
A20: Contribution (gross profit proxy) | B20: Margin | C20: =C8-C19 -> 3941 | D20: =D8-D19 -> 3858.575 | E20: =IF(D20=0,0,(C20-D20)/ABS(D20)) -> 0.021361513 | F20: Revenue − variable costs
A21: Contribution margin % | B21: Margin | C21: =IF(C8=0,0,C20/C8) -> 0.54343629 | D21: =IF(D8=0,0,D20/D8) -> 0.54537122 | E21: =IF(D21=0,0,(C21-D21)/ABS(D21)) -> -0.0035479056 | F21: Contribution / Revenue
A23: FIXED OPERATING COSTS
A24: Employee benefits expense | B24: Opex | C24: =Assumptions!B17 -> 274 | D24: =Assumptions!B35 -> 257 | E24: =IF(D24=0,0,(C24-D24)/ABS(D24)) -> 0.06614786 | F24: Fixed ₹ Cr lever
A25: Other cash fixed opex | B25: Opex | C25: =Assumptions!B18 -> 980 | D25: =Assumptions!B36 -> 1020 | E25: =IF(D25=0,0,(C25-D25)/ABS(D25)) -> -0.039215686 | F25: Selling + admin cash fixed
A26: Total cash fixed opex | B26: Opex | C26: =C24+C25 -> 1254 | D26: =D24+D25 -> 1277 | E26: =IF(D26=0,0,(C26-D26)/ABS(D26)) -> -0.018010963
A28: EBITDA | B28: Profit | C28: =C20-C26+C9 -> 2741 | D28: =D20-D26+D9 -> 2613.575 | E28: =IF(D28=0,0,(C28-D28)/ABS(D28)) -> 0.048755058 | F28: Contribution − cash fixed + other income
A29: Depreciation & amortization | B29: Profit | C29: =Assumptions!B19 -> 541 | D29: =Assumptions!B37 -> 495 | E29: =IF(D29=0,0,(C29-D29)/ABS(D29)) -> 0.092929293
A30: EBIT | B30: Profit | C30: =C28-C29 -> 2200 | D30: =D28-D29 -> 2118.575 | E30: =IF(D30=0,0,(C30-D30)/ABS(D30)) -> 0.038433853 | F30: EBITDA − D&A
A31: Finance cost | B31: Profit | C31: =Assumptions!B20 -> 210 | D31: =Assumptions!B38 -> 225 | E31: =IF(D31=0,0,(C31-D31)/ABS(D31)) -> -0.066666667
A32: Profit before tax (PBT) | B32: Profit | C32: =C30-C31 -> 1990 | D32: =D30-D31 -> 1893.575 | E32: =IF(D32=0,0,(C32-D32)/ABS(D32)) -> 0.050922197 | F32: EBIT − finance cost
A33: Tax expense | B33: Profit | C33: =C32*Assumptions!B22 -> 636.8 | D33: =D32*Assumptions!B40 -> 622.98618 | E33: =IF(D33=0,0,(C33-D33)/ABS(D33)) -> 0.022173566 | F33: PBT × tax rate
A34: Profit after tax (PAT) | B34: Profit | C34: =C32-C33 -> 1353.2 | D34: =D32-D33 -> 1270.5888 | E34: =IF(D34=0,0,(C34-D34)/ABS(D34)) -> 0.065018024 | F34: PBT − Tax
A36: EBITDA margin % | B36: Ratio | C36: =IF(C8=0,0,C28/C8) -> 0.3779647 | D36: =IF(D8=0,0,D28/D8) -> 0.36940285 | E36: =IF(D36=0,0,(C36-D36)/ABS(D36)) -> 0.023177553 | F36: EBITDA / Revenue
A37: PAT margin % | B37: Ratio | C37: =IF(C8=0,0,C34/C8) -> 0.1865968 | D37: =IF(D8=0,0,D34/D8) -> 0.1795851 | E37: =IF(D37=0,0,(C37-D37)/ABS(D37)) -> 0.039043891 | F37: PAT / Revenue
A39: KEY CHECKS
A40: P&L variable costs = Cost_Build? | C40: =C19-Cost_Build!C12 -> 0 | F40: Must be ~0
A41: P&L revenue = Assumptions revenue? | C41: =C8-Assumptions!B28 -> 0 | F41: Must be ~0

Sheet Scenario_CheatSheet
A1: Lever name | B1: Cell | C1: Base value | D1: What happens when you change it
A2: Cement sales volume | B2: Assumptions!B7 | C2: 14.0 MT | D2: Scales revenue AND all variable costs; fixed costs unchanged → operating leverage
A3: Blended realization | B3: Assumptions!B8 | C3: 5,260 ₹/t | D3: Moves net realization and revenue; costs unchanged → margin swing
A4: Trade discount | B4: Assumptions!B9 | C4: 80 ₹/t | D4: Lowers net realization without changing list price
A5: Fuel & power | B5: Assumptions!B11 | C5: 980 ₹/t | D5: Classic cement energy shock scenario
A6: Outbound freight | B6: Assumptions!B14 | C6: 620 ₹/t | D6: Logistics inflation / diesel / lead-distance
A7: Employee benefits | B7: Assumptions!B17 | C7: 274 ₹ Cr | D7: Wage inflation — fixed cost
A8: Finance cost | B8: Assumptions!B20 | C8: 210 ₹ Cr | D8: Rate hike / deleveraging
A9: Tax rate | B9: Assumptions!B22 | C9: 32% | D9: Effective tax sensitivity
